healthcheck/__init__.py
healthcheck/__main__.py
healthcheck/cli.py
healthcheck/config.py
healthcheck/healthcheck.py
healthcheck/influxdb/__init__.py
healthcheck/influxdb/main.py
healthcheck/mysql/__init__.py
healthcheck/mysql/main.py
healthcheck/rabbit_mq/__init__.py
healthcheck/rabbit_mq/main.py
healthcheck/redis/__init__.py
healthcheck/redis/main.py
healthcheck/rest_api/__init__.py
healthcheck/rest_api/main.py
health_util-0.0.10.dist-info/LICENSE
health_util-0.0.10.dist-info/METADATA
health_util-0.0.10.dist-info/WHEEL
health_util-0.0.10.dist-info/entry_points.txt
health_util-0.0.10.dist-info/top_level.txt
health_util-0.0.10.dist-info/RECORD
