Metadata-Version: 2.1
Name: health-util
Version: 0.0.10
Summary: A cli package for providing healthcheck
Home-page: https://github.com/mogu4iy/health-util/
Author: mogu4iy
Author-email: mogu4iy.kotygoroshko@gmail.com
License: MIT
Project-URL: Bug Tracker, https://github.com/mogu4iy/health-util//issues
Project-URL: repository, https://github.com/mogu4iy/health-util/
Classifier: Programming Language :: Python :: 3.8
Classifier: License :: OSI Approved :: MIT License
Classifier: Operating System :: OS Independent
Requires-Python: >=3.7
License-File: LICENSE
Requires-Dist: requests
Requires-Dist: click
Requires-Dist: redis
Requires-Dist: urllib3
Requires-Dist: mysql-connector-python
Requires-Dist: pika
Requires-Dist: python-dotenv
